docstring_extractor.py
docstring_extractor-0.4.0.dist-info/LICENSE
docstring_extractor-0.4.0.dist-info/WHEEL
docstring_extractor-0.4.0.dist-info/METADATA
docstring_extractor-0.4.0.dist-info/RECORD
