Metadata-Version: 2.1
Name: docstring-extractor
Version: 0.4.0
Summary: Get Python docstrings from files
Home-page: https://github.com/jkfran/docstring-extractor
License: GPL-3.0-or-later
Keywords: docstring,docstrings,parser
Author: Francisco Jimenez Cabrera
Author-email: jkfran@gmail.com
Requires-Python: >=3.6,<4.0
Classifier: License :: OSI Approved :: GNU General Public License v3 or later (GPLv3+)
Classifier: Programming Language :: Python :: 3
Classifier: Programming Language :: Python :: 3.6
Classifier: Programming Language :: Python :: 3.7
Classifier: Programming Language :: Python :: 3.8
Classifier: Topic :: Software Development :: Libraries :: Python Modules
Requires-Dist: docstring-parser (>=0.7.2,<0.8.0)
Project-URL: Documentation, https://github.com/jkfran/docstring-extractor
Project-URL: Repository, https://github.com/jkfran/docstring-extractor
